behaviortreepy-0.1.3.dist-info/RECORD
behaviortreepy-0.1.3.dist-info/WHEEL
behaviortreepy-0.1.3.dist-info/METADATA
behaviortreepy-0.1.3.dist-info/licenses/LICENSE
behaviortreepy/__init__.py
behaviortreepy/_behaviortreepy.cpython-38-darwin.so
behaviortreepy/.dylibs/libsodium.26.dylib
behaviortreepy/.dylibs/libzmq.5.dylib
